Metadata-Version: 2.1
Name: vialactea
Version: 0.0.661
Summary: UNKNOWN
Author: Sirius Technology Studio
Maintainer: Sirius Technology Studio
Maintainer-email: 
License: UNKNOWN
Platform: UNKNOWN
License-File: LICENSE.txt
